chatllm/__init__.py
chatllm/chatllm.py
chatllm/qa.py
chatllm/utils.py
chatllm/applications/Question2Answer.py
chatllm/applications/__init__.py
chatllm/applications/ann4qa.py
chatllm/applications/chatbase.py
chatllm/applications/chatdoc.py
chatllm/applications/chatpdf.py
chatllm/applications/chatweb.py
chatllm/applications/crawler4qa.py
chatllm/applications/pipeline.py
chatllm/clis/README.md
chatllm/clis/__init__.py
chatllm/clis/cli.py
chatllm/kb/FaissANN.py
chatllm/kb/__init__.py
chatllm/kb/kbqa.py
chatllm/knowledge_base/__init__.py
chatllm/knowledge_base/lite.py
chatllm/parse_utils/__init__.py
chatllm/parse_utils/doc_embedding.py
chatllm/parse_utils/doc_parse.py
chatllm/textsplitter/__init__.py
chatllm/textsplitter/chinese_text_splitter.py
chatllm/uis/__init__.py
chatllm/uis/gradio_ui.py
ChatDocument-2023.4.25.9.50.0.dist-info/AUTHORS.rst
ChatDocument-2023.4.25.9.50.0.dist-info/LICENSE
ChatDocument-2023.4.25.9.50.0.dist-info/METADATA
ChatDocument-2023.4.25.9.50.0.dist-info/WHEEL
ChatDocument-2023.4.25.9.50.0.dist-info/entry_points.txt
ChatDocument-2023.4.25.9.50.0.dist-info/top_level.txt
ChatDocument-2023.4.25.9.50.0.dist-info/RECORD
